{"ai_packaging_infos":[],"ai_packaging_report_info":{"caption_id_list":[],"task_id":"","text_style":"","tos_id":"","video_category":""},"commercial_music_category_ids":[],"pc_feature_flag":0,"recognize_tasks":[{"items":[{"content":"young people wander through the street lost","duration":833333,"segment_id":"35296E91-EBB4-4baf-A1D2-60CACDCCF354","start":300000}],"language":"en-US","recognize_type":"subtitle","scene":"multiple","task_id":"c54bbb21-7ea0-49b9-9d99-db6120053d85"},{"items":[{"content":"young people wander through the street lost","duration":833333,"segment_id":"35296E91-EBB4-4baf-A1D2-60CACDCCF354","start":300000}],"language":"en-US","recognize_type":"subtitle","scene":"multiple","task_id":"8dfa1ad0-e2be-4828-bec0-bbb768ec44a4"}],"template_item_infos":[],"unlock_template_ids":[]}